nrtk_explorer/__init__.py
nrtk_explorer/__main__.py
nrtk_explorer/app/__init__.py
nrtk_explorer/app/applet.py
nrtk_explorer/app/core.py
nrtk_explorer/app/jupyter.py
nrtk_explorer/app/main.py
nrtk_explorer/app/trame_utils.py
nrtk_explorer/app/features/__init__.py
nrtk_explorer/app/features/datasets.py
nrtk_explorer/app/features/embeddings.py
nrtk_explorer/app/features/export.py
nrtk_explorer/app/features/filtering.py
nrtk_explorer/app/features/images.py
nrtk_explorer/app/features/inference.py
nrtk_explorer/app/features/parameters.py
nrtk_explorer/app/features/transforms.py
nrtk_explorer/app/images/annotations.py
nrtk_explorer/app/images/cache.py
nrtk_explorer/app/images/image_ids.py
nrtk_explorer/app/images/image_meta.py
nrtk_explorer/app/images/image_server.py
nrtk_explorer/app/images/images.py
nrtk_explorer/app/images/stateful_annotations.py
nrtk_explorer/app/test/__init__.py
nrtk_explorer/app/test/quasar.py
nrtk_explorer/app/test/vuetify2.py
nrtk_explorer/app/test/vuetify3.py
nrtk_explorer/app/ui/__init__.py
nrtk_explorer/app/ui/collapsible_card.py
nrtk_explorer/app/ui/image_list.css
nrtk_explorer/app/ui/image_list.py
nrtk_explorer/app/ui/layout.py
nrtk_explorer/library/__init__.py
nrtk_explorer/library/annotations.py
nrtk_explorer/library/app_config.py
nrtk_explorer/library/dataset.py
nrtk_explorer/library/debounce.py
nrtk_explorer/library/dimension_reducers.py
nrtk_explorer/library/embeddings_extractor.py
nrtk_explorer/library/filtering.py
nrtk_explorer/library/multiprocess_predictor.py
nrtk_explorer/library/nrtk_transforms.py
nrtk_explorer/library/nrtk_transforms.yaml
nrtk_explorer/library/predictor.py
nrtk_explorer/library/scoring.py
nrtk_explorer/library/serialization_helpers.py
nrtk_explorer/library/transforms.py
nrtk_explorer/library/yaml_transforms.py
nrtk_explorer/module/.gitignore
nrtk_explorer/module/__init__.py
nrtk_explorer/module/serve/nrtk_explorer.umd.js
nrtk_explorer/module/serve/nrtk_explorer.umd.js.map
nrtk_explorer/module/serve/styles.css
nrtk_explorer-0.8.3.dist-info/METADATA
nrtk_explorer-0.8.3.dist-info/WHEEL
nrtk_explorer-0.8.3.dist-info/entry_points.txt
nrtk_explorer-0.8.3.dist-info/licenses/LICENSE
nrtk_explorer-0.8.3.dist-info/RECORD
