Metadata-Version: 2.4
Name: nrtk-explorer
Version: 0.8.3
Summary: Model Visualizer
Author-email: Alessandro Genova <alessandro.genova@kitware.com>, Vicente Adolfo Bolea Sanchez <vicente.bolea@kitware.com>
License-File: LICENSE
Keywords: Application,Framework,Interactive,Python,Web
Classifier: Development Status :: 4 - Beta
Classifier: Environment :: Web Environment
Classifier: License :: Other/Proprietary License
Classifier: Natural Language :: English
Classifier: Operating System :: OS Independent
Classifier: Programming Language :: JavaScript
Classifier: Programming Language :: Python :: 3 :: Only
Classifier: Topic :: Software Development :: Libraries :: Application Frameworks
Classifier: Topic :: Software Development :: Libraries :: Python Modules
Requires-Python: <3.13,>=3.10
Requires-Dist: accelerate
Requires-Dist: datasets[vision]
Requires-Dist: kwcoco
Requires-Dist: nrtk[albumentations,diffusion,headless,pillow,pybsm,scikit-image,waterdroplet]==0.26.0
Requires-Dist: numpy
Requires-Dist: pillow
Requires-Dist: psutil
Requires-Dist: pybsm
Requires-Dist: scikit-learn>=1.6.0
Requires-Dist: smqtk-image-io
Requires-Dist: tabulate
Requires-Dist: timm>=1.0.3
Requires-Dist: torch
Requires-Dist: torchvision
Requires-Dist: trame-alerts
Requires-Dist: trame-annotations>=0.5.0
Requires-Dist: trame-quasar
Requires-Dist: trame>=3.7
Requires-Dist: transformers==4.52.1
Requires-Dist: umap-learn
Requires-Dist: wslink>=2.3.2
Provides-Extra: dev
Requires-Dist: black; extra == 'dev'
Requires-Dist: flake8; extra == 'dev'
Requires-Dist: mypy; extra == 'dev'
Requires-Dist: pre-commit; extra == 'dev'
Requires-Dist: pytest; extra == 'dev'
Requires-Dist: tabulate; extra == 'dev'
Requires-Dist: types-pyyaml; extra == 'dev'
Provides-Extra: package
Requires-Dist: build<1.3.0; extra == 'package'
Requires-Dist: python-semantic-release; extra == 'package'
Requires-Dist: setuptools; extra == 'package'
Requires-Dist: wheel; extra == 'package'
Provides-Extra: web
Requires-Dist: trame-vtk; extra == 'web'
Requires-Dist: trame-vuetify; extra == 'web'
